surveytomato/__init__.py
surveytomato/formHandler.py
surveytomato/items.py
surveytomato-0.1.2.dist-info/WHEEL
surveytomato-0.1.2.dist-info/entry_points.txt
surveytomato-0.1.2.dist-info/METADATA
surveytomato-0.1.2.dist-info/RECORD
