Metadata-Version: 2.3
Name: surveytomato
Version: 0.1.2
Summary: Build dynamic surveys with Python
Author: Alexander Schau
Author-email: Alexander Schau <hello@surveytomato.com>
Requires-Dist: websockets>=15.0.1
Requires-Python: >=3.13
